{"TotalIdleTime":1031,"TotalEmptyRelocationTime":979,"EventsInsertedByALNS":19,"Scenario":{"name":"Gen_Data_300_0.5_6_Run4"},"TotalElapsedTime":2393.75,"UnservicedOnlineRequests":25,"TotalRideTime":14257,"nTaxi":25,"TotalNumberOfRequestsOverlapIdleVehicle":43,"UnservicedOfflineRequests":0,"AverageResponseTime":19.94,"AveragePercentRideSharing":11.231,"TotalIdleTimeWithCustomer":52,"TotalDirectRideTime":5547,"TotalDriveTimeToNearestIdleVehicle":974,"nOnlineRequests":120,"TotalCost":27925.25227049538,"TotalDistance":11831.64664754034,"nOfflineRequests":180,"TotalActualRideTime":6322}