{"TotalIdleTime":5570,"TotalEmptyRelocationTime":4871,"EventsInsertedByALNS":18,"Scenario":{"name":"Gen_Data_500_0.7_10_Run2"},"TotalElapsedTime":3634.54,"UnservicedOnlineRequests":52,"TotalRideTime":29825,"nTaxi":52,"TotalNumberOfRequestsOverlapIdleVehicle":496,"UnservicedOfflineRequests":0,"AverageResponseTime":7.27,"AveragePercentRideSharing":2.938,"TotalIdleTimeWithCustomer":10,"TotalDirectRideTime":9537,"TotalDriveTimeToNearestIdleVehicle":8898,"nOnlineRequests":500,"TotalCost":56612.622617653346,"TotalDistance":21877.344520876988,"nOfflineRequests":0,"TotalActualRideTime":9980}