{"TotalIdleTime":205,"TotalEmptyRelocationTime":479,"EventsInsertedByALNS":0,"Scenario":{"name":"Gen_Data_500_0.5_8_Run1"},"TotalElapsedTime":1203.37,"UnservicedOnlineRequests":0,"TotalRideTime":22202,"nTaxi":1,"TotalNumberOfRequestsOverlapIdleVehicle":0,"UnservicedOfflineRequests":1,"AverageResponseTime":0.0,"AveragePercentRideSharing":16.955,"TotalIdleTimeWithCustomer":18,"TotalDirectRideTime":10682,"TotalDriveTimeToNearestIdleVehicle":0,"nOnlineRequests":200,"TotalCost":6512.9990518242985,"TotalDistance":19466.651184343653,"nOfflineRequests":300,"TotalActualRideTime":13074}