{"TotalIdleTime":1894,"TotalEmptyRelocationTime":2465,"EventsInsertedByALNS":18,"Scenario":{"name":"Gen_Data_300_0.7_6_Run4"},"TotalElapsedTime":2423.49,"UnservicedOnlineRequests":92,"TotalRideTime":14316,"nTaxi":92,"TotalNumberOfRequestsOverlapIdleVehicle":256,"UnservicedOfflineRequests":0,"AverageResponseTime":8.08,"AveragePercentRideSharing":8.456,"TotalIdleTimeWithCustomer":0,"TotalDirectRideTime":4505,"TotalDriveTimeToNearestIdleVehicle":7788,"nOnlineRequests":300,"TotalCost":94350.10249218668,"TotalDistance":11339.002040381305,"nOfflineRequests":0,"TotalActualRideTime":5251}