{"TotalIdleTime":362,"TotalEmptyRelocationTime":770,"EventsInsertedByALNS":14,"Scenario":{"name":"Gen_Data_100_0.7_10_Run5"},"TotalElapsedTime":354.37,"UnservicedOnlineRequests":1,"TotalRideTime":5948,"nTaxi":1,"TotalNumberOfRequestsOverlapIdleVehicle":8,"UnservicedOfflineRequests":0,"AverageResponseTime":8.86,"AveragePercentRideSharing":4.583,"TotalIdleTimeWithCustomer":2,"TotalDirectRideTime":1879,"TotalDriveTimeToNearestIdleVehicle":270,"nOnlineRequests":40,"TotalCost":2015.5215641618431,"TotalDistance":5080.3595640818285,"nOfflineRequests":60,"TotalActualRideTime":1980}