{"TotalIdleTime":485,"TotalEmptyRelocationTime":334,"EventsInsertedByALNS":12,"Scenario":{"name":"Gen_Data_100_0.5_7_Run1"},"TotalElapsedTime":426.86,"UnservicedOnlineRequests":13,"TotalRideTime":4862,"nTaxi":13,"TotalNumberOfRequestsOverlapIdleVehicle":15,"UnservicedOfflineRequests":0,"AverageResponseTime":10.67,"AveragePercentRideSharing":10.42,"TotalIdleTimeWithCustomer":21,"TotalDirectRideTime":1875,"TotalDriveTimeToNearestIdleVehicle":371,"nOnlineRequests":40,"TotalCost":13955.099335754454,"TotalDistance":3935.1324532662284,"nOfflineRequests":60,"TotalActualRideTime":2294}