{"TotalIdleTime":674,"TotalEmptyRelocationTime":415,"EventsInsertedByALNS":10,"Scenario":{"name":"Gen_Data_100_0.7_10_Run1"},"TotalElapsedTime":181.57,"UnservicedOnlineRequests":1,"TotalRideTime":6040,"nTaxi":1,"TotalNumberOfRequestsOverlapIdleVehicle":14,"UnservicedOfflineRequests":0,"AverageResponseTime":4.53,"AveragePercentRideSharing":7.05,"TotalIdleTimeWithCustomer":8,"TotalDirectRideTime":1879,"TotalDriveTimeToNearestIdleVehicle":425,"nOnlineRequests":40,"TotalCost":2038.9028789016454,"TotalDistance":4858.824254357383,"nOfflineRequests":60,"TotalActualRideTime":2079}