{"TotalIdleTime":325,"TotalEmptyRelocationTime":456,"EventsInsertedByALNS":7,"Scenario":{"name":"Gen_Data_100_0.5_8_Run1"},"TotalElapsedTime":191.07,"UnservicedOnlineRequests":17,"TotalRideTime":4683,"nTaxi":17,"TotalNumberOfRequestsOverlapIdleVehicle":14,"UnservicedOfflineRequests":0,"AverageResponseTime":4.77,"AveragePercentRideSharing":8.014,"TotalIdleTimeWithCustomer":6,"TotalDirectRideTime":1558,"TotalDriveTimeToNearestIdleVehicle":566,"nOnlineRequests":40,"TotalCost":17885.91371942234,"TotalDistance":3934.9353083701303,"nOfflineRequests":60,"TotalActualRideTime":1792}