{"TotalIdleTime":883,"TotalEmptyRelocationTime":1386,"EventsInsertedByALNS":0,"Scenario":{"name":"Gen_Data_500_0.7_7_Run3"},"TotalElapsedTime":1201.02,"UnservicedOnlineRequests":0,"TotalRideTime":27661,"nTaxi":2,"TotalNumberOfRequestsOverlapIdleVehicle":0,"UnservicedOfflineRequests":2,"AverageResponseTime":0.0,"AveragePercentRideSharing":11.457,"TotalIdleTimeWithCustomer":123,"TotalDirectRideTime":10934,"TotalDriveTimeToNearestIdleVehicle":0,"nOnlineRequests":500,"TotalCost":7485.017019776995,"TotalDistance":24262.61481925953,"nOfflineRequests":0,"TotalActualRideTime":12845}