{"TotalIdleTime":285,"TotalEmptyRelocationTime":475,"EventsInsertedByALNS":12,"Scenario":{"name":"Gen_Data_100_0.5_7_Run5"},"TotalElapsedTime":498.25,"UnservicedOnlineRequests":15,"TotalRideTime":4874,"nTaxi":15,"TotalNumberOfRequestsOverlapIdleVehicle":8,"UnservicedOfflineRequests":0,"AverageResponseTime":12.46,"AveragePercentRideSharing":15.739,"TotalIdleTimeWithCustomer":21,"TotalDirectRideTime":1938,"TotalDriveTimeToNearestIdleVehicle":148,"nOnlineRequests":40,"TotalCost":15983.568620807893,"TotalDistance":4151.194969939012,"nOfflineRequests":60,"TotalActualRideTime":2532}