{"TotalIdleTime":1055,"TotalEmptyRelocationTime":2704,"EventsInsertedByALNS":15,"Scenario":{"name":"Gen_Data_500_0.5_10_Run4"},"TotalElapsedTime":4016.31,"UnservicedOnlineRequests":69,"TotalRideTime":23093,"nTaxi":69,"TotalNumberOfRequestsOverlapIdleVehicle":47,"UnservicedOfflineRequests":0,"AverageResponseTime":20.08,"AveragePercentRideSharing":11.642,"TotalIdleTimeWithCustomer":20,"TotalDirectRideTime":9467,"TotalDriveTimeToNearestIdleVehicle":1065,"nOnlineRequests":200,"TotalCost":73672.52588130237,"TotalDistance":19841.836948879107,"nOfflineRequests":300,"TotalActualRideTime":10895}