{"TotalIdleTime":481,"TotalEmptyRelocationTime":340,"EventsInsertedByALNS":5,"Scenario":{"name":"Gen_Data_100_0.5_6_Run4"},"TotalElapsedTime":516.46,"UnservicedOnlineRequests":20,"TotalRideTime":4803,"nTaxi":20,"TotalNumberOfRequestsOverlapIdleVehicle":5,"UnservicedOfflineRequests":0,"AverageResponseTime":12.9,"AveragePercentRideSharing":13.552,"TotalIdleTimeWithCustomer":0,"TotalDirectRideTime":1725,"TotalDriveTimeToNearestIdleVehicle":203,"nOnlineRequests":40,"TotalCost":20872.010920403056,"TotalDistance":3913.514248662431,"nOfflineRequests":60,"TotalActualRideTime":2034}