{"TotalIdleTime":281,"TotalEmptyRelocationTime":422,"EventsInsertedByALNS":13,"Scenario":{"name":"Gen_Data_100_0.5_1_Run4"},"TotalElapsedTime":192.56,"UnservicedOnlineRequests":15,"TotalRideTime":4901,"nTaxi":15,"TotalNumberOfRequestsOverlapIdleVehicle":14,"UnservicedOfflineRequests":0,"AverageResponseTime":4.81,"AveragePercentRideSharing":10.578,"TotalIdleTimeWithCustomer":41,"TotalDirectRideTime":1773,"TotalDriveTimeToNearestIdleVehicle":508,"nOnlineRequests":40,"TotalCost":15936.49962665501,"TotalDistance":4184.528584188231,"nOfflineRequests":60,"TotalActualRideTime":2085}