{"TotalIdleTime":776,"TotalEmptyRelocationTime":1838,"EventsInsertedByALNS":14,"Scenario":{"name":"Gen_Data_300_0.5_2_Run1"},"TotalElapsedTime":2385.77,"UnservicedOnlineRequests":40,"TotalRideTime":14358,"nTaxi":40,"TotalNumberOfRequestsOverlapIdleVehicle":30,"UnservicedOfflineRequests":0,"AverageResponseTime":19.88,"AveragePercentRideSharing":11.381,"TotalIdleTimeWithCustomer":61,"TotalDirectRideTime":6060,"TotalDriveTimeToNearestIdleVehicle":717,"nOnlineRequests":120,"TotalCost":42816.5087436137,"TotalDistance":12260.059624000045,"nOfflineRequests":180,"TotalActualRideTime":7024}