{"TotalIdleTime":92,"TotalEmptyRelocationTime":201,"EventsInsertedByALNS":0,"Scenario":{"name":"Gen_Data_300_0.5_1_Run3"},"TotalElapsedTime":1201.16,"UnservicedOnlineRequests":0,"TotalRideTime":13700,"nTaxi":2,"TotalNumberOfRequestsOverlapIdleVehicle":0,"UnservicedOfflineRequests":2,"AverageResponseTime":0.0,"AveragePercentRideSharing":13.9,"TotalIdleTimeWithCustomer":11,"TotalDirectRideTime":5762,"TotalDriveTimeToNearestIdleVehicle":0,"nOnlineRequests":120,"TotalCost":5197.113649769926,"TotalDistance":12104.395595733655,"nOfflineRequests":180,"TotalActualRideTime":6802}