{"TotalIdleTime":373,"TotalEmptyRelocationTime":233,"EventsInsertedByALNS":9,"Scenario":{"name":"Gen_Data_100_0.5_9_Run2"},"TotalElapsedTime":543.01,"UnservicedOnlineRequests":20,"TotalRideTime":4808,"nTaxi":20,"TotalNumberOfRequestsOverlapIdleVehicle":16,"UnservicedOfflineRequests":0,"AverageResponseTime":13.57,"AveragePercentRideSharing":17.331,"TotalIdleTimeWithCustomer":18,"TotalDirectRideTime":1791,"TotalDriveTimeToNearestIdleVehicle":516,"nOnlineRequests":40,"TotalCost":20923.524888409967,"TotalDistance":4018.141701543777,"nOfflineRequests":60,"TotalActualRideTime":2371}