{"TotalIdleTime":365,"TotalEmptyRelocationTime":417,"EventsInsertedByALNS":11,"Scenario":{"name":"Gen_Data_100_0.5_10_Run2"},"TotalElapsedTime":192.78,"UnservicedOnlineRequests":16,"TotalRideTime":4773,"nTaxi":16,"TotalNumberOfRequestsOverlapIdleVehicle":8,"UnservicedOfflineRequests":0,"AverageResponseTime":4.81,"AveragePercentRideSharing":5.902,"TotalIdleTimeWithCustomer":16,"TotalDirectRideTime":1564,"TotalDriveTimeToNearestIdleVehicle":182,"nOnlineRequests":40,"TotalCost":16888.557889372496,"TotalDistance":3985.974869954905,"nOfflineRequests":60,"TotalActualRideTime":1730}