{"TotalIdleTime":267,"TotalEmptyRelocationTime":402,"EventsInsertedByALNS":7,"Scenario":{"name":"Gen_Data_100_0.5_8_Run2"},"TotalElapsedTime":459.01,"UnservicedOnlineRequests":12,"TotalRideTime":4731,"nTaxi":12,"TotalNumberOfRequestsOverlapIdleVehicle":8,"UnservicedOfflineRequests":0,"AverageResponseTime":11.47,"AveragePercentRideSharing":6.957,"TotalIdleTimeWithCustomer":0,"TotalDirectRideTime":1662,"TotalDriveTimeToNearestIdleVehicle":320,"nOnlineRequests":40,"TotalCost":12933.159344417552,"TotalDistance":4015.9505537305113,"nOfflineRequests":60,"TotalActualRideTime":1862}