{"TotalIdleTime":3185,"TotalEmptyRelocationTime":1926,"EventsInsertedByALNS":3,"Scenario":{"name":"Gen_Data_100_0.7_2_Run3"},"TotalElapsedTime":880.36,"UnservicedOnlineRequests":41,"TotalRideTime":6840,"nTaxi":41,"TotalNumberOfRequestsOverlapIdleVehicle":99,"UnservicedOfflineRequests":0,"AverageResponseTime":8.8,"AveragePercentRideSharing":1.316,"TotalIdleTimeWithCustomer":0,"TotalDirectRideTime":1258,"TotalDriveTimeToNearestIdleVehicle":2627,"nOnlineRequests":100,"TotalCost":41608.75,"TotalDistance":3340.7783724921865,"nOfflineRequests":0,"TotalActualRideTime":1303}