{"TotalIdleTime":511,"TotalEmptyRelocationTime":437,"EventsInsertedByALNS":12,"Scenario":{"name":"Gen_Data_100_0.7_10_Run4"},"TotalElapsedTime":308.19,"UnservicedOnlineRequests":1,"TotalRideTime":6037,"nTaxi":1,"TotalNumberOfRequestsOverlapIdleVehicle":8,"UnservicedOfflineRequests":0,"AverageResponseTime":7.7,"AveragePercentRideSharing":3.624,"TotalIdleTimeWithCustomer":0,"TotalDirectRideTime":1879,"TotalDriveTimeToNearestIdleVehicle":212,"nOnlineRequests":40,"TotalCost":2006.2915487667647,"TotalDistance":5018.2509739272455,"nOfflineRequests":60,"TotalActualRideTime":1944}