{"TotalIdleTime":1824,"TotalEmptyRelocationTime":1668,"EventsInsertedByALNS":14,"Scenario":{"name":"Gen_Data_300_0.7_7_Run1"},"TotalElapsedTime":2409.0,"UnservicedOnlineRequests":7,"TotalRideTime":19186,"nTaxi":7,"TotalNumberOfRequestsOverlapIdleVehicle":50,"UnservicedOfflineRequests":0,"AverageResponseTime":20.07,"AveragePercentRideSharing":5.764,"TotalIdleTimeWithCustomer":41,"TotalDirectRideTime":6790,"TotalDriveTimeToNearestIdleVehicle":1421,"nOnlineRequests":120,"TotalCost":10067.769002834484,"TotalDistance":15846.309703063707,"nOfflineRequests":180,"TotalActualRideTime":7369}