{"TotalIdleTime":1012,"TotalEmptyRelocationTime":1209,"EventsInsertedByALNS":0,"Scenario":{"name":"Gen_Data_500_0.7_2_Run5"},"TotalElapsedTime":1202.19,"UnservicedOnlineRequests":0,"TotalRideTime":27267,"nTaxi":4,"TotalNumberOfRequestsOverlapIdleVehicle":0,"UnservicedOfflineRequests":4,"AverageResponseTime":0.0,"AveragePercentRideSharing":12.905,"TotalIdleTimeWithCustomer":134,"TotalDirectRideTime":11171,"TotalDriveTimeToNearestIdleVehicle":0,"nOnlineRequests":500,"TotalCost":9459.480109560645,"TotalDistance":23742.195109754888,"nOfflineRequests":0,"TotalActualRideTime":13419}