{"TotalIdleTime":413,"TotalEmptyRelocationTime":607,"EventsInsertedByALNS":0,"Scenario":{"name":"Gen_Data_100_0.7_10_Run5"},"TotalElapsedTime":1201.11,"UnservicedOnlineRequests":0,"TotalRideTime":5661,"nTaxi":10,"TotalNumberOfRequestsOverlapIdleVehicle":0,"UnservicedOfflineRequests":10,"AverageResponseTime":0.0,"AveragePercentRideSharing":7.736,"TotalIdleTimeWithCustomer":34,"TotalDirectRideTime":1754,"TotalDriveTimeToNearestIdleVehicle":0,"nOnlineRequests":100,"TotalCost":10965.208623931321,"TotalDistance":4790.826554669243,"nOfflineRequests":0,"TotalActualRideTime":2061}