{"TotalIdleTime":2262,"TotalEmptyRelocationTime":3428,"EventsInsertedByALNS":19,"Scenario":{"name":"Gen_Data_500_0.7_9_Run3"},"TotalElapsedTime":4006.97,"UnservicedOnlineRequests":5,"TotalRideTime":30564,"nTaxi":5,"TotalNumberOfRequestsOverlapIdleVehicle":63,"UnservicedOfflineRequests":0,"AverageResponseTime":20.03,"AveragePercentRideSharing":3.077,"TotalIdleTimeWithCustomer":36,"TotalDirectRideTime":10360,"TotalDriveTimeToNearestIdleVehicle":1606,"nOnlineRequests":200,"TotalCost":10043.223400006755,"TotalDistance":25789.093802843534,"nOfflineRequests":300,"TotalActualRideTime":10787}