{"TotalIdleTime":2067,"TotalEmptyRelocationTime":1754,"EventsInsertedByALNS":10,"Scenario":{"name":"Gen_Data_300_0.7_4_Run4"},"TotalElapsedTime":2365.75,"UnservicedOnlineRequests":0,"TotalRideTime":19110,"nTaxi":0,"TotalNumberOfRequestsOverlapIdleVehicle":54,"UnservicedOfflineRequests":0,"AverageResponseTime":19.71,"AveragePercentRideSharing":2.848,"TotalIdleTimeWithCustomer":15,"TotalDirectRideTime":6297,"TotalDriveTimeToNearestIdleVehicle":1501,"nOnlineRequests":120,"TotalCost":3050.0920578086825,"TotalDistance":15486.428536997766,"nOfflineRequests":180,"TotalActualRideTime":6526}