{"TotalIdleTime":1563,"TotalEmptyRelocationTime":2654,"EventsInsertedByALNS":17,"Scenario":{"name":"Gen_Data_300_0.7_8_Run4"},"TotalElapsedTime":2409.08,"UnservicedOnlineRequests":2,"TotalRideTime":19399,"nTaxi":2,"TotalNumberOfRequestsOverlapIdleVehicle":28,"UnservicedOfflineRequests":0,"AverageResponseTime":20.07,"AveragePercentRideSharing":5.643,"TotalIdleTimeWithCustomer":15,"TotalDirectRideTime":7453,"TotalDriveTimeToNearestIdleVehicle":975,"nOnlineRequests":120,"TotalCost":5078.098601445278,"TotalDistance":16297.392338362291,"nOfflineRequests":180,"TotalActualRideTime":7919}