{"TotalIdleTime":1414,"TotalEmptyRelocationTime":2608,"EventsInsertedByALNS":6,"Scenario":{"name":"Gen_Data_300_0.7_2_Run4"},"TotalElapsedTime":2385.99,"UnservicedOnlineRequests":2,"TotalRideTime":19255,"nTaxi":2,"TotalNumberOfRequestsOverlapIdleVehicle":34,"UnservicedOfflineRequests":0,"AverageResponseTime":19.88,"AveragePercentRideSharing":3.803,"TotalIdleTimeWithCustomer":0,"TotalDirectRideTime":6889,"TotalDriveTimeToNearestIdleVehicle":1032,"nOnlineRequests":120,"TotalCost":5025.937988735235,"TotalDistance":16319.679890719122,"nOfflineRequests":180,"TotalActualRideTime":7124}