{"TotalIdleTime":574,"TotalEmptyRelocationTime":801,"EventsInsertedByALNS":0,"Scenario":{"name":"Gen_Data_300_0.7_1_Run2"},"TotalElapsedTime":1200.84,"UnservicedOnlineRequests":0,"TotalRideTime":16543,"nTaxi":5,"TotalNumberOfRequestsOverlapIdleVehicle":0,"UnservicedOfflineRequests":5,"AverageResponseTime":0.0,"AveragePercentRideSharing":12.859,"TotalIdleTimeWithCustomer":23,"TotalDirectRideTime":6400,"TotalDriveTimeToNearestIdleVehicle":0,"nOnlineRequests":300,"TotalCost":8261.294702062612,"TotalDistance":14464.401417801648,"nOfflineRequests":0,"TotalActualRideTime":7657}